canvas_tools/__init__.py
canvas_tools/__main__.py
canvas_tools/client.py
canvas_tools/submissions.py
canvas_instructor_tools-0.1.0a0.dist-info/METADATA
canvas_instructor_tools-0.1.0a0.dist-info/WHEEL
canvas_instructor_tools-0.1.0a0.dist-info/entry_points.txt
canvas_instructor_tools-0.1.0a0.dist-info/licenses/LICENSE
canvas_instructor_tools-0.1.0a0.dist-info/RECORD
