Metadata-Version: 2.4
Name: canvas-instructor-tools
Version: 0.1.0a0
Summary: A collection of tools for automating Canvas LMS instructor operations.
Author-email: George Perdrizet <george@perdrizet.org>
License-File: LICENSE
Classifier: License :: OSI Approved :: MIT License
Classifier: Operating System :: OS Independent
Classifier: Programming Language :: Python :: 3
Classifier: Programming Language :: Python :: 3.11
Classifier: Programming Language :: Python :: 3.12
Classifier: Programming Language :: Python :: 3.13
Requires-Python: >=3.11
Requires-Dist: canvasapi>=3.0.0
Requires-Dist: python-dotenv>=1.0.0
